geyser/__init__.py
geyser/__main__.py
geyser/context.py
geyser/geyser.py
geyser/schema.json
geyser/typedef.py
geyser/utility.py
geyser-0.4.10.dist-info/LICENSE
geyser-0.4.10.dist-info/METADATA
geyser-0.4.10.dist-info/WHEEL
geyser-0.4.10.dist-info/entry_points.txt
geyser-0.4.10.dist-info/top_level.txt
geyser-0.4.10.dist-info/RECORD
