Metadata-Version: 2.1
Name: geyser
Version: 0.4.10
Summary: Compose and execute python objects
Home-page: https://github.com/chenrz925/geyser
Author: Runze Chen
Author-email: chenrz925@icloud.com
License: UNKNOWN
Project-URL: Bug Reports, https://github.com/chenrz925/geyser/issues
Project-URL: Source, https://github.com/chenrz925/geyser
Keywords: sample,setuptools,development
Platform: UNKNOWN
Classifier: Development Status :: 2 - Pre-Alpha
Classifier: Intended Audience :: Developers
Classifier: Topic :: Software Development :: Build Tools
Classifier: License :: OSI Approved :: Apache Software License
Classifier: Programming Language :: Python :: 3
Classifier: Programming Language :: Python :: 3.6
Classifier: Programming Language :: Python :: 3.7
Classifier: Programming Language :: Python :: 3.8
Classifier: Programming Language :: Python :: 3.9
Classifier: Programming Language :: Python :: 3 :: Only
Classifier: Environment :: Console
Requires-Python: >=3.6, <4
License-File: LICENSE
Requires-Dist: taskflow (>=4.6.1)
Requires-Dist: greenlet
Requires-Dist: ruamel.yaml (>=0.17.16)
Requires-Dist: toml (>=0.10.2)
Requires-Dist: colorlog (>=6.4.1)
Requires-Dist: pyhocon (>=0.3.58)
Requires-Dist: setproctitle (>=1.2.2)
Requires-Dist: more-itertools (>=8.8.0)
